microlens_submit/__init__.py
microlens_submit/error_messages.py
microlens_submit/text_symbols.py
microlens_submit/tier_validation.py
microlens_submit/utils.py
microlens_submit/validate_parameters.py
microlens_submit/assets/github-desktop_logo.png
microlens_submit/assets/rges-pit_logo.png
microlens_submit/cli/__init__.py
microlens_submit/cli/__main__.py
microlens_submit/cli/main.py
microlens_submit/cli/commands/__init__.py
microlens_submit/cli/commands/dossier.py
microlens_submit/cli/commands/export.py
microlens_submit/cli/commands/init.py
microlens_submit/cli/commands/solutions.py
microlens_submit/cli/commands/validation.py
microlens_submit/dossier/__init__.py
microlens_submit/dossier/dashboard.py
microlens_submit/dossier/event_page.py
microlens_submit/dossier/full_report.py
microlens_submit/dossier/solution_page.py
microlens_submit/dossier/utils.py
microlens_submit/models/__init__.py
microlens_submit/models/event.py
microlens_submit/models/solution.py
microlens_submit/models/submission.py
microlens_submit-0.16.4.dist-info/licenses/LICENSE
microlens_submit-0.16.4.dist-info/METADATA
microlens_submit-0.16.4.dist-info/WHEEL
microlens_submit-0.16.4.dist-info/entry_points.txt
microlens_submit-0.16.4.dist-info/top_level.txt
microlens_submit-0.16.4.dist-info/RECORD
