Metadata-Version: 2.4
Name: microlens-submit
Version: 0.16.4
Summary: A tool for managing and submitting microlensing solutions
Home-page: https://github.com/AmberLee2427/microlens-submit
Author: Amber Malpas
Author-email: Amber Malpas <malpas.1@osu.edu>, Roman Science Platform Team <roman-science-platform@stsci.edu>
License: MIT
Project-URL: Homepage, https://github.com/AmberLee2427/microlens-submit
Project-URL: Repository, https://github.com/AmberLee2427/microlens-submit
Keywords: astronomy,microlensing,data-challenge,submission,roman
Classifier: Development Status :: 4 - Beta
Classifier: Intended Audience :: Science/Research
Classifier: License :: OSI Approved :: MIT License
Classifier: Operating System :: OS Independent
Classifier: Programming Language :: Python :: 3
Classifier: Programming Language :: Python :: 3.8
Classifier: Programming Language :: Python :: 3.9
Classifier: Programming Language :: Python :: 3.10
Classifier: Programming Language :: Python :: 3.11
Classifier: Programming Language :: Python :: 3.12
Classifier: Topic :: Scientific/Engineering :: Astronomy
Classifier: Topic :: Scientific/Engineering :: Physics
Requires-Python: >=3.8
License-File: LICENSE
Requires-Dist: pydantic>=2.0.0
Requires-Dist: typer[all]>=0.9.0
Requires-Dist: rich>=13.0.0
Requires-Dist: pyyaml>=6.0
Requires-Dist: markdown>=3.4.0
Requires-Dist: psutil>=5.9.0
Requires-Dist: importlib_resources>=1.0.0; python_version < "3.9"
Provides-Extra: dev
Requires-Dist: pytest; extra == "dev"
Requires-Dist: pytest-cov; extra == "dev"
Requires-Dist: build; extra == "dev"
Requires-Dist: twine; extra == "dev"
Requires-Dist: pre-commit; extra == "dev"
Requires-Dist: black; extra == "dev"
Requires-Dist: isort; extra == "dev"
Requires-Dist: sphinx; extra == "dev"
Requires-Dist: sphinx_rtd_theme; extra == "dev"
Requires-Dist: importlib_resources; extra == "dev"
Requires-Dist: python-dotenv; extra == "dev"
Dynamic: author
Dynamic: home-page
Dynamic: license-file
Dynamic: requires-python
